mycloudpy/__init__.py
mycloudpy-0.0.2.dist-info/LICENSE
mycloudpy-0.0.2.dist-info/METADATA
mycloudpy-0.0.2.dist-info/WHEEL
mycloudpy-0.0.2.dist-info/top_level.txt
mycloudpy-0.0.2.dist-info/RECORD
